rotal/__init__.py
rotal/__main__.py
rotal/cli.py
rotal-0.1.0.dist-info/DESCRIPTION.rst
rotal-0.1.0.dist-info/entry_points.txt
rotal-0.1.0.dist-info/METADATA
rotal-0.1.0.dist-info/metadata.json
rotal-0.1.0.dist-info/RECORD
rotal-0.1.0.dist-info/top_level.txt
rotal-0.1.0.dist-info/WHEEL
