Metadata-Version: 2.0
Name: rotal
Version: 0.1.0
Summary: Get a running count of occurrences from a stream.
Home-page: https://github.com/bwbaugh/rotal
Author: Wesley Baugh
Author-email: wesley@bwbaugh.com
License: UNKNOWN
Platform: UNKNOWN
Classifier: Development Status :: 3 - Alpha
Classifier: Environment :: Console
Classifier: Intended Audience :: Developers
Classifier: Programming Language :: Python :: 2.7
Classifier: Topic :: Utilities
Requires-Dist: Click
